ag_ui_strands/__init__.py
ag_ui_strands/agent.py
ag_ui_strands/config.py
ag_ui_strands/endpoint.py
ag_ui_strands/types.py
ag_ui_strands/utils.py
ag_ui_strands-0.1.0.dist-info/METADATA
ag_ui_strands-0.1.0.dist-info/WHEEL
ag_ui_strands-0.1.0.dist-info/RECORD
