Metadata-Version: 2.4
Name: ag_ui_strands
Version: 0.1.0
Author: AG-UI Contributors
Requires-Python: <3.14,>=3.12
Requires-Dist: ag-ui-protocol>=0.1.10
Requires-Dist: fastapi>=0.115.12
Requires-Dist: strands-agents>=1.15.0
